simplecrud/__init__.py
simplecrud/sync_sqlalchemy.py
simplecrud-1.0.0.dist-info/entry_points.txt
simplecrud-1.0.0.dist-info/LICENSE
simplecrud-1.0.0.dist-info/WHEEL
simplecrud-1.0.0.dist-info/METADATA
simplecrud-1.0.0.dist-info/RECORD
